presidio_evaluator/__init__.py
presidio_evaluator/data_objects.py
presidio_evaluator/span_to_tag.py
presidio_evaluator/validation.py
presidio_evaluator/data_generator/__init__.py
presidio_evaluator/data_generator/presidio_data_generator.py
presidio_evaluator/data_generator/presidio_pseudonymize.py
presidio_evaluator/data_generator/faker_extensions/__init__.py
presidio_evaluator/data_generator/faker_extensions/data_objects.py
presidio_evaluator/data_generator/faker_extensions/providers.py
presidio_evaluator/data_generator/faker_extensions/record_generator.py
presidio_evaluator/data_generator/faker_extensions/records_faker.py
presidio_evaluator/data_generator/faker_extensions/span_generator.py
presidio_evaluator/data_generator/raw_data/FakeNameGenerator.com_1000_American.csv
presidio_evaluator/data_generator/raw_data/companies_and_organizations.csv
presidio_evaluator/data_generator/raw_data/nationalities.csv
presidio_evaluator/data_generator/raw_data/religions.csv
presidio_evaluator/data_generator/raw_data/templates.txt
presidio_evaluator/data_generator/raw_data/us_driver_license_format.yaml
presidio_evaluator/dataset_formatters/__init__.py
presidio_evaluator/dataset_formatters/conll_formatter.py
presidio_evaluator/dataset_formatters/dataset_formatter.py
presidio_evaluator/dataset_formatters/i2b2_formatter.py
presidio_evaluator/evaluation/__init__.py
presidio_evaluator/evaluation/evaluation_result.py
presidio_evaluator/evaluation/evaluator.py
presidio_evaluator/evaluation/model_error.py
presidio_evaluator/evaluation/scorers.py
presidio_evaluator/experiment_tracking/__init__.py
presidio_evaluator/experiment_tracking/experiment_tracker.py
presidio_evaluator/models/__init__.py
presidio_evaluator/models/base_model.py
presidio_evaluator/models/crf_model.py
presidio_evaluator/models/flair_model.py
presidio_evaluator/models/flair_train.py
presidio_evaluator/models/presidio_analyzer_wrapper.py
presidio_evaluator/models/presidio_recognizer_wrapper.py
privy_presidio_utils-0.0.71.dist-info/LICENSE
privy_presidio_utils-0.0.71.dist-info/METADATA
privy_presidio_utils-0.0.71.dist-info/WHEEL
privy_presidio_utils-0.0.71.dist-info/top_level.txt
privy_presidio_utils-0.0.71.dist-info/RECORD
