Metadata-Version: 2.1
Name: privy-presidio-utils
Version: 0.0.71
Summary: Read the latest Real Python tutorials
Home-page: https://www.github.com/microsoft/presidio-research
License: MIT License        
Project-URL: Homepage, https://github.com/benkilimnik/presidio-research
Keywords: nlp,pii
Classifier: License :: OSI Approved :: MIT License
Classifier: Programming Language :: Python
Classifier: Programming Language :: Python :: 3
License-File: LICENSE
Requires-Dist: spacy (>=3.2.0)
Requires-Dist: numpy (>=1.20.2)
Requires-Dist: pandas (>=1.2.4)
Requires-Dist: tqdm (>=4.60.0)
Requires-Dist: haikunator (>=2.1.0)
Requires-Dist: schwifty
Requires-Dist: faker (>=9.6.0)
Requires-Dist: scikit-learn
Requires-Dist: flair
Requires-Dist: stanza
Requires-Dist: spacy-stanza
Requires-Dist: sklearn-crfsuite
Requires-Dist: pytest (>=6.2.3)
Requires-Dist: presidio-analyzer
Requires-Dist: presidio-anonymizer
Requires-Dist: requests (>=2.25.1)
Requires-Dist: xmltodict (>=0.12.0)
Requires-Dist: python-dotenv
Provides-Extra: dev
Requires-Dist: black ; extra == 'dev'
Requires-Dist: bumpver ; extra == 'dev'
Requires-Dist: isort ; extra == 'dev'
Requires-Dist: pip-tools ; extra == 'dev'
Requires-Dist: pytest ; extra == 'dev'
